calendar_event_engine/Runner.py
calendar_event_engine/__init__.py
calendar_event_engine/db/__init__.py
calendar_event_engine/db/combine_driver.py
calendar_event_engine/db/db_cache.py
calendar_event_engine/db/event_source_driver.py
calendar_event_engine/db/uploaded_events_driver.py
calendar_event_engine/filter.py
calendar_event_engine/logger.py
calendar_event_engine/parser/__init__.py
calendar_event_engine/parser/package.py
calendar_event_engine/parser/submission.py
calendar_event_engine/publishers/__init__.py
calendar_event_engine/publishers/abc_publisher.py
calendar_event_engine/publishers/mobilizon/__init__.py
calendar_event_engine/publishers/mobilizon/api.py
calendar_event_engine/publishers/mobilizon/gql_requests.py
calendar_event_engine/publishers/mobilizon/types.py
calendar_event_engine/publishers/mobilizon/uploader.py
calendar_event_engine/scrapers/__init__.py
calendar_event_engine/scrapers/abc_scraper.py
calendar_event_engine/scrapers/google_calendar/__init__.py
calendar_event_engine/scrapers/google_calendar/api.py
calendar_event_engine/scrapers/google_calendar/scraper.py
calendar_event_engine/scrapers/ical/__init__.py
calendar_event_engine/scrapers/ical/scraper.py
calendar_event_engine/scrapers/statics/__init__.py
calendar_event_engine/scrapers/statics/scraper.py
calendar_event_engine/types/__init__.py
calendar_event_engine/types/custom_scraper.py
calendar_event_engine/types/generics.py
calendar_event_engine/types/submission.py
calendar_event_engine/types/submission_handlers.py
calendar_event_engine/utils/__init__.py
calendar_event_engine/utils/location.py
calendar_event_engine-0.1.4.dist-info/LICENSE
calendar_event_engine-0.1.4.dist-info/METADATA
calendar_event_engine-0.1.4.dist-info/WHEEL
calendar_event_engine-0.1.4.dist-info/RECORD
