Metadata-Version: 2.1
Name: calendar_event_engine
Version: 0.1.4
Summary: 
Author: Ezequiel Valencia
Requires-Python: >=3.10,<4.0
Classifier: Programming Language :: Python :: 3
Classifier: Programming Language :: Python :: 3.10
Classifier: Programming Language :: Python :: 3.11
Classifier: Programming Language :: Python :: 3.12
Requires-Dist: aiohttp (>=3.10.10,<4.0.0)
Requires-Dist: beautifulsoup4 (>=4.13.4,<5.0.0)
Requires-Dist: geopy (>=2.4.1,<3.0.0)
Requires-Dist: google-api-python-client (>=2.127.0,<3.0.0)
Requires-Dist: google-auth-httplib2 (>=0.2.0,<0.3.0)
Requires-Dist: google-auth-oauthlib (>=1.2.0,<2.0.0)
Requires-Dist: gql (==3.5.0)
Requires-Dist: icalendar (>=6.0.1,<7.0.0)
Requires-Dist: pandas (>=2.2.3,<3.0.0)
Requires-Dist: pydantic (>=2.7.0,<3.0.0)
Requires-Dist: pytest (>=8.2.2,<9.0.0)
Requires-Dist: requests (>=2.31.0,<3.0.0)
Requires-Dist: requests-toolbelt (>=1.0.0,<2.0.0)
Requires-Dist: slack_sdk (>=3.32.0,<4.0.0)
Requires-Dist: tenacity (>=8.2.3,<9.0.0)
Requires-Dist: validators (>=0.34.0,<0.35.0)
